[{"line":1,"elements":[{"line":4,"name":"","description":"","type":"background","keyword":"Background","steps":[{"name":"def baseUrl = 'https:\/\/www.krafttechexlab.com\/sw\/api\/v1\/allusers'","result":{"duration":307000,"status":"passed"},"match":{"location":"karate","arguments":[]},"keyword":"*","line":5,"doc_string":{"content_type":"","value":"23:25:42.659 skipping bootstrap configuration: could not find or read file: classpath:karate-config.js","line":5}}]},{"line":7,"name":"path params","description":"","id":"path-params","type":"scenario","keyword":"Scenario","steps":[{"name":"def expected =","result":{"duration":530100,"status":"passed"},"match":{"location":"karate","arguments":[]},"keyword":"*","line":9,"doc_string":{"content_type":"","value":"[\n  {\n    \"id\": 1,\n    \"name\": \"MercanS\",\n    \"email\": \"afmercan@gmail.com\",\n    \"password\": \"$2y$10$VOqhVBmA5aPuEyd1z7YID.SV3\/9QIFQ.dSVTGIetNUbNQx2gMFEAK\",\n    \"about\": \"About\",\n    \"terms\": \"16\",\n    \"date\": \"2022-09-12 20:50:38\",\n    \"job\": \"Manual Tester\",\n    \"company\": \"Mrcn Software\",\n    \"website\": \"https:\/\/www.krafttechexlab.com\/\",\n    \"location\": \"Turkey\",\n    \"skills\": [\n\"PHP\",\n\"Java\"\n    ],\n    \"github\": \"aFmGit\",\n    \"twitter\": \"aFmTwitter\",\n    \"facebook\": \"aFmFace\",\n    \"youtube\": \"aFmYoutube\",\n    \"linkedin\": \"aFmLinkedin\",\n    \"instagram\": \"aFmInstagram\",\n    \"avatar\": \"1\",\n    \"admin\": \"1\",\n    \"education\": [\n{\n  \"id\": 44,\n  \"school\": \"School or Bootcamp\",\n  \"degree\": \"Degree\",\n  \"study\": \"Study\",\n  \"description\": \"Program Description\",\n  \"fromdate\": \"2000-12-02\",\n  \"todate\": \"2004-12-01\",\n  \"date\": \"2022-09-25 01:03:22\"\n},\n{\n  \"id\": 120,\n  \"school\": \"School\",\n  \"degree\": \"Degree\",\n  \"study\": \"Study\",\n  \"description\": \"Description\",\n  \"fromdate\": \"2020-05-05\",\n  \"todate\": \"2020-05-05\",\n  \"date\": \"2023-01-08 23:01:24\"\n},\n{\n  \"id\": 121,\n  \"school\": \"School\",\n  \"degree\": \"Degree\",\n  \"study\": \"Study\",\n  \"description\": \"Description\",\n  \"fromdate\": \"2020-05-05\",\n  \"todate\": \"2020-05-05\",\n  \"date\": \"2023-01-08 23:02:06\"\n},\n{\n  \"id\": 122,\n  \"school\": \"School\",\n  \"degree\": \"Degree\",\n  \"study\": \"Study\",\n  \"description\": \"Description\",\n  \"fromdate\": \"2020-05-05\",\n  \"todate\": \"2020-05-05\",\n  \"date\": \"2023-01-08 23:02:51\"\n}\n    ],\n    \"experience\": [\n{\n  \"id\": 38,\n  \"job\": \"Junior Developer1\",\n  \"company\": \"Kraft Techex1\",\n  \"location\": \"USA2\",\n  \"description\": \"Description2\",\n  \"fromdate\": \"2019-01-01\",\n  \"todate\": \"2022-10-09\",\n  \"date\": \"2022-09-05 18:10:26\"\n},\n{\n  \"id\": 56,\n  \"job\": \"Junior Developer1\",\n  \"company\": \"Kraft Techex\",\n  \"location\": \"USA\",\n  \"description\": \"Description\",\n  \"fromdate\": \"2020-01-10\",\n  \"todate\": \"2022-10-09\",\n  \"date\": \"2022-10-09 17:52:44\"\n},\n{\n  \"id\": 189,\n  \"job\": \"Junior Developer\",\n  \"company\": \"Kraft Techex\",\n  \"location\": \"USA\",\n  \"description\": \"Description\",\n  \"fromdate\": \"2000-01-01\",\n  \"todate\": \"2023-01-21\",\n  \"date\": \"2023-01-08 17:46:07\"\n}\n    ]\n  }\n]","line":9}},{"name":"url baseUrl + '\/getbyid'","result":{"duration":4782300,"status":"passed"},"match":{"location":"karate","arguments":[]},"keyword":"Given","line":113},{"name":"path '1'","result":{"duration":232600,"status":"passed"},"match":{"location":"karate","arguments":[]},"keyword":"And","line":114},{"name":"method GET","result":{"duration":122079900,"status":"passed"},"match":{"location":"karate","arguments":[]},"keyword":"When","line":115,"doc_string":{"content_type":"","value":"23:25:42.667 request:\n1 > GET https:\/\/www.krafttechexlab.com\/sw\/api\/v1\/allusers\/getbyid\/1\n1 > Accept-Encoding: gzip,deflate\n1 > Connection: Keep-Alive\n1 > Host: www.krafttechexlab.com\n1 > User-Agent: Apache-HttpClient\/4.5.11 (Java\/1.8.0_352)\n\n23:25:42.786 response time in milliseconds: 119.05\n1 < 200\n1 < Access-Control-Allow-Methods: GET\n1 < Access-Control-Allow-Origin: *\n1 < Connection: Upgrade, Keep-Alive\n1 < Content-Type: application\/json; charset=UTF-8\n1 < Date: Sat, 11 Feb 2023 20:26:22 GMT\n1 < Keep-Alive: timeout=2, max=100\n1 < Server: Apache\/2\n1 < Upgrade: h2,h2c\n1 < Vary: Accept-Encoding,User-Agent\n[{\"id\":1,\"name\":\"MercanS\",\"email\":\"afmercan@gmail.com\",\"password\":\"$2y$10$VOqhVBmA5aPuEyd1z7YID.SV3\\\/9QIFQ.dSVTGIetNUbNQx2gMFEAK\",\"about\":\"About\",\"terms\":\"16\",\"date\":\"2022-09-12 20:50:38\",\"job\":\"Manual Tester\",\"company\":\"Mrcn Software\",\"website\":\"https:\\\/\\\/www.krafttechexlab.com\\\/\",\"location\":\"Turkey\",\"skills\":[\"PHP\",\"Java\"],\"github\":\"aFmGit\",\"twitter\":\"aFmTwitter\",\"facebook\":\"aFmFace\",\"youtube\":\"aFmYoutube\",\"linkedin\":\"aFmLinkedin\",\"instagram\":\"aFmInstagram\",\"avatar\":\"1\",\"admin\":\"1\",\"education\":[{\"id\":44,\"school\":\"School or Bootcamp\",\"degree\":\"Degree\",\"study\":\"Study\",\"description\":\"Program Description\",\"fromdate\":\"2000-12-02\",\"todate\":\"2004-12-01\",\"date\":\"2022-09-25 01:03:22\"},{\"id\":120,\"school\":\"School\",\"degree\":\"Degree\",\"study\":\"Study\",\"description\":\"Description\",\"fromdate\":\"2020-05-05\",\"todate\":\"2020-05-05\",\"date\":\"2023-01-08 23:01:24\"},{\"id\":121,\"school\":\"School\",\"degree\":\"Degree\",\"study\":\"Study\",\"description\":\"Description\",\"fromdate\":\"2020-05-05\",\"todate\":\"2020-05-05\",\"date\":\"2023-01-08 23:02:06\"},{\"id\":122,\"school\":\"School\",\"degree\":\"Degree\",\"study\":\"Study\",\"description\":\"Description\",\"fromdate\":\"2020-05-05\",\"todate\":\"2020-05-05\",\"date\":\"2023-01-08 23:02:51\"}],\"experience\":[{\"id\":38,\"job\":\"Junior Developer1\",\"company\":\"Kraft Techex1\",\"location\":\"USA2\",\"description\":\"Description2\",\"fromdate\":\"2019-01-01\",\"todate\":\"2022-10-09\",\"date\":\"2022-09-05 18:10:26\"},{\"id\":56,\"job\":\"Junior Developer1\",\"company\":\"Kraft Techex\",\"location\":\"USA\",\"description\":\"Description\",\"fromdate\":\"2020-01-10\",\"todate\":\"2022-10-09\",\"date\":\"2022-10-09 17:52:44\"},{\"id\":189,\"job\":\"Junior Developer\",\"company\":\"Kraft Techex\",\"location\":\"USA\",\"description\":\"Description\",\"fromdate\":\"2000-01-01\",\"todate\":\"2023-01-21\",\"date\":\"2023-01-08 17:46:07\"}]}]","line":115}},{"name":"status 200","result":{"duration":11000,"status":"passed"},"match":{"location":"karate","arguments":[]},"keyword":"Then","line":116},{"name":"print response","result":{"duration":521500,"status":"passed"},"match":{"location":"karate","arguments":[]},"keyword":"*","line":117,"doc_string":{"content_type":"","value":"23:25:42.787 [print] [\n  {\n    \"date\": \"2022-09-12 20:50:38\",\n    \"youtube\": \"aFmYoutube\",\n    \"website\": \"https:\/\/www.krafttechexlab.com\/\",\n    \"github\": \"aFmGit\",\n    \"education\": [\n      {\n        \"date\": \"2022-09-25 01:03:22\",\n        \"study\": \"Study\",\n        \"todate\": \"2004-12-01\",\n        \"school\": \"School or Bootcamp\",\n        \"degree\": \"Degree\",\n        \"description\": \"Program Description\",\n        \"id\": 44,\n        \"fromdate\": \"2000-12-02\"\n      },\n      {\n        \"date\": \"2023-01-08 23:01:24\",\n        \"study\": \"Study\",\n        \"todate\": \"2020-05-05\",\n        \"school\": \"School\",\n        \"degree\": \"Degree\",\n        \"description\": \"Description\",\n        \"id\": 120,\n        \"fromdate\": \"2020-05-05\"\n      },\n      {\n        \"date\": \"2023-01-08 23:02:06\",\n        \"study\": \"Study\",\n        \"todate\": \"2020-05-05\",\n        \"school\": \"School\",\n        \"degree\": \"Degree\",\n        \"description\": \"Description\",\n        \"id\": 121,\n        \"fromdate\": \"2020-05-05\"\n      },\n      {\n        \"date\": \"2023-01-08 23:02:51\",\n        \"study\": \"Study\",\n        \"todate\": \"2020-05-05\",\n        \"school\": \"School\",\n        \"degree\": \"Degree\",\n        \"description\": \"Description\",\n        \"id\": 122,\n        \"fromdate\": \"2020-05-05\"\n      }\n    ],\n    \"facebook\": \"aFmFace\",\n    \"about\": \"About\",\n    \"admin\": \"1\",\n    \"linkedin\": \"aFmLinkedin\",\n    \"instagram\": \"aFmInstagram\",\n    \"avatar\": \"1\",\n    \"experience\": [\n      {\n        \"date\": \"2022-09-05 18:10:26\",\n        \"todate\": \"2022-10-09\",\n        \"description\": \"Description2\",\n        \"company\": \"Kraft Techex1\",\n        \"location\": \"USA2\",\n        \"id\": 38,\n        \"job\": \"Junior Developer1\",\n        \"fromdate\": \"2019-01-01\"\n      },\n      {\n        \"date\": \"2022-10-09 17:52:44\",\n        \"todate\": \"2022-10-09\",\n        \"description\": \"Description\",\n        \"company\": \"Kraft Techex\",\n        \"location\": \"USA\",\n        \"id\": 56,\n        \"job\": \"Junior Developer1\",\n        \"fromdate\": \"2020-01-10\"\n      },\n      {\n        \"date\": \"2023-01-08 17:46:07\",\n        \"todate\": \"2023-01-21\",\n        \"description\": \"Description\",\n        \"company\": \"Kraft Techex\",\n        \"location\": \"USA\",\n        \"id\": 189,\n        \"job\": \"Junior Developer\",\n        \"fromdate\": \"2000-01-01\"\n      }\n    ],\n    \"skills\": [\n      \"PHP\",\n      \"Java\"\n    ],\n    \"password\": \"$2y$10$VOqhVBmA5aPuEyd1z7YID.SV3\/9QIFQ.dSVTGIetNUbNQx2gMFEAK\",\n    \"twitter\": \"aFmTwitter\",\n    \"terms\": \"16\",\n    \"name\": \"MercanS\",\n    \"company\": \"Mrcn Software\",\n    \"location\": \"Turkey\",\n    \"id\": 1,\n    \"job\": \"Manual Tester\",\n    \"email\": \"afmercan@gmail.com\"\n  }\n]","line":117}},{"name":"match response == expected","result":{"duration":507800,"status":"passed"},"match":{"location":"karate","arguments":[]},"keyword":"*","line":118}]},{"line":4,"name":"","description":"","type":"background","keyword":"Background","steps":[{"name":"def baseUrl = 'https:\/\/www.krafttechexlab.com\/sw\/api\/v1\/allusers'","result":{"duration":229300,"status":"passed"},"match":{"location":"karate","arguments":[]},"keyword":"*","line":5,"doc_string":{"content_type":"","value":"23:25:42.876 skipping bootstrap configuration: could not find or read file: classpath:karate-config.js","line":5}}]},{"line":120,"name":"Query Parama","description":"","id":"query-parama","type":"scenario","keyword":"Scenario","steps":[{"name":"url baseUrl","result":{"duration":7700,"status":"passed"},"match":{"location":"karate","arguments":[]},"keyword":"Given","line":121},{"name":"path 'alluser'","result":{"duration":2561600,"status":"passed"},"match":{"location":"karate","arguments":[]},"keyword":"When","line":122},{"name":"param skills = 'PHP'","result":{"duration":2916600,"status":"passed"},"match":{"location":"karate","arguments":[]},"keyword":"*","line":123},{"name":"param pagesize = 25","result":{"duration":2769900,"status":"passed"},"match":{"location":"karate","arguments":[]},"keyword":"*","line":124},{"name":"param page = 1","result":{"duration":3019100,"status":"passed"},"match":{"location":"karate","arguments":[]},"keyword":"*","line":125},{"name":"method GET","result":{"duration":214367600,"status":"passed"},"match":{"location":"karate","arguments":[]},"keyword":"*","line":126,"doc_string":{"content_type":"","value":"23:25:42.891 request:\n1 > GET https:\/\/www.krafttechexlab.com\/sw\/api\/v1\/allusers\/alluser?skills=PHP&pagesize=25&page=1\n1 > Accept-Encoding: gzip,deflate\n1 > Connection: Keep-Alive\n1 > Host: www.krafttechexlab.com\n1 > User-Agent: Apache-HttpClient\/4.5.11 (Java\/1.8.0_352)\n\n23:25:43.099 response time in milliseconds: 204.15\n1 < 200\n1 < Access-Control-Allow-Origin: *\n1 < Connection: Upgrade, Keep-Alive\n1 < Content-Type: application\/json; charset=UTF-8\n1 < Date: Sat, 11 Feb 2023 20:26:22 GMT\n1 < Keep-Alive: timeout=2, max=100\n1 < Server: Apache\/2\n1 < Upgrade: h2,h2c\n1 < Vary: Accept-Encoding,User-Agent\n[{\"id\":1,\"name\":\"MercanS\",\"email\":\"afmercan@gmail.com\",\"password\":\"$2y$10$VOqhVBmA5aPuEyd1z7YID.SV3\\\/9QIFQ.dSVTGIetNUbNQx2gMFEAK\",\"about\":\"About\",\"terms\":\"16\",\"date\":\"2022-09-12 20:50:38\",\"job\":\"Manual Tester\",\"company\":\"Mrcn Software\",\"website\":\"https:\\\/\\\/www.krafttechexlab.com\\\/\",\"location\":\"Turkey\",\"skills\":[\"PHP\",\"Java\"],\"github\":\"aFmGit\",\"twitter\":\"aFmTwitter\",\"facebook\":\"aFmFace\",\"youtube\":\"aFmYoutube\",\"linkedin\":\"aFmLinkedin\",\"instagram\":\"aFmInstagram\",\"avatar\":\"1\",\"admin\":\"1\",\"education\":[{\"id\":44,\"school\":\"School or Bootcamp\",\"degree\":\"Degree\",\"study\":\"Study\",\"description\":\"Program Description\",\"fromdate\":\"2000-12-02\",\"todate\":\"2004-12-01\",\"date\":\"2022-09-25 01:03:22\"},{\"id\":120,\"school\":\"School\",\"degree\":\"Degree\",\"study\":\"Study\",\"description\":\"Description\",\"fromdate\":\"2020-05-05\",\"todate\":\"2020-05-05\",\"date\":\"2023-01-08 23:01:24\"},{\"id\":121,\"school\":\"School\",\"degree\":\"Degree\",\"study\":\"Study\",\"description\":\"Description\",\"fromdate\":\"2020-05-05\",\"todate\":\"2020-05-05\",\"date\":\"2023-01-08 23:02:06\"},{\"id\":122,\"school\":\"School\",\"degree\":\"Degree\",\"study\":\"Study\",\"description\":\"Description\",\"fromdate\":\"2020-05-05\",\"todate\":\"2020-05-05\",\"date\":\"2023-01-08 23:02:51\"}],\"experience\":[{\"id\":38,\"job\":\"Junior Developer1\",\"company\":\"Kraft Techex1\",\"location\":\"USA2\",\"description\":\"Description2\",\"fromdate\":\"2019-01-01\",\"todate\":\"2022-10-09\",\"date\":\"2022-09-05 18:10:26\"},{\"id\":56,\"job\":\"Junior Developer1\",\"company\":\"Kraft Techex\",\"location\":\"USA\",\"description\":\"Description\",\"fromdate\":\"2020-01-10\",\"todate\":\"2022-10-09\",\"date\":\"2022-10-09 17:52:44\"},{\"id\":189,\"job\":\"Junior Developer\",\"company\":\"Kraft Techex\",\"location\":\"USA\",\"description\":\"Description\",\"fromdate\":\"2000-01-01\",\"todate\":\"2023-01-21\",\"date\":\"2023-01-08 17:46:07\"}]},{\"id\":24,\"name\":\"mike\",\"email\":\"mike@gmail.com\",\"password\":\"$2y$10$KWJ2f3iTUFvkvzTS7\\\/O0AOBmfwYknjscuwdA8n4c25gkzFqi9tswW\",\"about\":\"About\",\"terms\":\"2\",\"date\":\"2022-09-12 20:50:38\",\"job\":\"Developer\",\"company\":\"Stark - Mayer\",\"website\":\"https:\\\/\\\/mike.org\",\"location\":\"Lake Chrisberg\",\"skills\":[\"PHP\",\"Java\"],\"github\":\"\",\"twitter\":\"\",\"facebook\":\"\",\"youtube\":\"\",\"linkedin\":\"\",\"instagram\":\"\",\"avatar\":\"1\",\"admin\":\"0 or 1\",\"education\":[{\"id\":48,\"school\":\"yk6\",\"degree\":\"56u\",\"study\":\"56u56\",\"description\":\"56u56\",\"fromdate\":\"5656-05-06\",\"todate\":\"65656-05-05\",\"date\":\"2022-11-25 14:09:19\"},{\"id\":50,\"school\":\"Krafttech Technologie Bootcamp\",\"degree\":\"QA Engineer\",\"study\":\"Tester\",\"description\":\"Bringing a good test engineer to the IT industry\",\"fromdate\":\"2022-07-25\",\"todate\":\"2022-03-25\",\"date\":\"2022-11-28 14:01:46\"},{\"id\":51,\"school\":\"Krafttech Technologie Bootcamp\",\"degree\":\"QA Engineer\",\"study\":\"Tester\",\"description\":\"Bringing a good test engineer to the IT industry\",\"fromdate\":\"2022-07-25\",\"todate\":\"2022-03-25\",\"date\":\"2022-11-28 14:03:04\"},{\"id\":52,\"school\":\"Krafttech Technologie Bootcamp\",\"degree\":\"QA Engineer\",\"study\":\"Tester\",\"description\":\"Bringing a good test engineer to the IT industry\",\"fromdate\":\"2022-07-25\",\"todate\":\"2022-03-25\",\"date\":\"2022-11-28 14:06:14\"},{\"id\":53,\"school\":\"Krafttech Technologie Bootcamp\",\"degree\":\"QA Engineer\",\"study\":\"Tester\",\"description\":\"Bringing a good test engineer to the IT industry\",\"fromdate\":\"2022-07-25\",\"todate\":\"2022-03-25\",\"date\":\"2022-11-28 14:07:28\"},{\"id\":54,\"school\":\"werewrwe\",\"degree\":\"werwerwe\",\"study\":\"rwerwer\",\"description\":\"tyutyutyuuty\",\"fromdate\":\"2222-07-25\",\"todate\":\"2223-12-12\",\"date\":\"2022-11-28 14:08:04\"},{\"id\":55,\"school\":\"Krafttech Technologie Bootcamp\",\"degree\":\"QA Engineer\",\"study\":\"Tester\",\"description\":\"Bringing a good test engineer to the IT industry\",\"fromdate\":\"2022-07-25\",\"todate\":\"2022-03-25\",\"date\":\"2022-11-28 14:10:59\"},{\"id\":56,\"school\":\"Krafttech Technologie Bootcamp\",\"degree\":\"QA Engineer\",\"study\":\"Tester\",\"description\":\"Bringing a good test engineer to the IT industry\",\"fromdate\":\"2022-07-25\",\"todate\":\"2022-03-25\",\"date\":\"2022-11-28 14:13:05\"},{\"id\":57,\"school\":\"Krafttech Technologie Bootcamp\",\"degree\":\"QA Engineer\",\"study\":\"Tester\",\"description\":\"Bringing a good test engineer to the IT industry\",\"fromdate\":\"2022-07-25\",\"todate\":\"2022-03-25\",\"date\":\"2022-11-28 14:17:50\"},{\"id\":58,\"school\":\"fsdfsd\",\"degree\":\"sdfsdfsd\",\"study\":\"fsdfsd\",\"description\":\"dfwewewerw\",\"fromdate\":\"1111-04-21\",\"todate\":\"2222-04-23\",\"date\":\"2022-11-28 14:18:40\"},{\"id\":59,\"school\":\"Krafttech Technologie Bootcamp\",\"degree\":\"QA Engineer\",\"study\":\"Tester\",\"description\":\"Bringing a good test engineer to the IT industry\",\"fromdate\":\"2022-07-25\",\"todate\":\"2022-03-25\",\"date\":\"2022-11-28 14:20:14\"}],\"experience\":[{\"id\":87,\"job\":\"QA\",\"company\":\"GHAN IT\",\"location\":\"ANKARA\",\"description\":\"Cool Workplace\",\"fromdate\":\"2020-02-02\",\"todate\":\"2022-02-02\",\"date\":\"2022-11-23 20:49:15\"},{\"id\":89,\"job\":\"QA\",\"company\":\"GAHN TI\",\"location\":\"Izmir\",\"description\":\"Cool Workplace\",\"fromdate\":\"2020-02-02\",\"todate\":\"2020-02-02\",\"date\":\"2022-11-23 20:50:16\"},{\"id\":91,\"job\":\"QA\",\"company\":\"KraftTech\",\"location\":\"Ankara\",\"description\":\"Nice work\",\"fromdate\":\"12021-02-11\",\"todate\":\"12022-02-11\",\"date\":\"2022-11-23 20:51:58\"},{\"id\":93,\"job\":\"Tester\",\"company\":\"GHAN IT\",\"location\":\"ankara\",\"description\":\"Coll Workplace\",\"fromdate\":\"2020-02-02\",\"todate\":\"2022-02-02\",\"date\":\"2022-11-23 21:01:53\"},{\"id\":94,\"job\":\"QA\",\"company\":\"KraftTech\",\"location\":\"Ankara\",\"description\":\"Nice work\",\"fromdate\":\"12021-02-11\",\"todate\":\"12022-02-11\",\"date\":\"2022-11-23 21:48:00\"},{\"id\":95,\"job\":\"qa\",\"company\":\"\\u015firket\",\"location\":\"usa\",\"description\":\"erferergergergergerg\",\"fromdate\":\"2022-02-22\",\"todate\":\"2023-06-22\",\"date\":\"2022-11-24 11:39:44\"},{\"id\":99,\"job\":\"QA\",\"company\":\"Ghan It\",\"location\":\"Ankara\",\"description\":\"Cool Workplace\",\"fromdate\":\"2001-12-20\",\"todate\":\"2021-04-14\",\"date\":\"2022-11-25 13:42:40\"},{\"id\":100,\"job\":\"QA\",\"company\":\"GHAN IT\",\"location\":\"ANKARA\",\"description\":\"Cool Workplace\",\"fromdate\":\"2020-02-02\",\"todate\":\"2022-02-02\",\"date\":\"2022-11-25 16:57:13\"},{\"id\":101,\"job\":\"SDET\",\"company\":\"Krafttech\",\"location\":\"Madrid\",\"description\":\"\",\"fromdate\":\"2022-07-25\",\"todate\":\"Now\",\"date\":\"2022-11-25 16:57:14\"},{\"id\":273,\"job\":\"Junior Developer\",\"company\":\"Kraft Techex\",\"location\":\"USA\",\"description\":\"Description\",\"fromdate\":\"2011-01-01\",\"todate\":\"2012-01-01\",\"date\":\"2023-02-01 18:53:16\"},{\"id\":274,\"job\":\"Junior Developer\",\"company\":\"Kraft Techex\",\"location\":\"USA\",\"description\":\"Description\",\"fromdate\":\"2014-01-01\",\"todate\":\"2015-01-01\",\"date\":\"2023-02-01 18:53:58\"},{\"id\":275,\"job\":\"Junior Developer\",\"company\":\"Kraft Techex\",\"location\":\"USA\",\"description\":\"Description\",\"fromdate\":\"2014-01-01\",\"todate\":\"2015-01-01\",\"date\":\"2023-02-01 18:54:24\"},{\"id\":276,\"job\":\"Junior Developer\",\"company\":\"Kraft Techex\",\"location\":\"USA\",\"description\":\"Description\",\"fromdate\":\"2014-01-01\",\"todate\":\"2015-01-01\",\"date\":\"2023-02-01 18:55:19\"},{\"id\":277,\"job\":\"Junior Developer\",\"company\":\"Kraft Techex\",\"location\":\"USA\",\"description\":\"Description\",\"fromdate\":\"2014-01-01\",\"todate\":\"2015-01-01\",\"date\":\"2023-02-01 18:57:11\"},{\"id\":278,\"job\":\"Junior Developer\",\"company\":\"Kraft Techex\",\"location\":\"USA\",\"description\":\"Description\",\"fromdate\":\"2014-01-01\",\"todate\":\"2015-01-01\",\"date\":\"2023-02-01 18:57:19\"},{\"id\":279,\"job\":\"Junior Developer\",\"company\":\"Kraft Techex\",\"location\":\"USA\",\"description\":\"Description\",\"fromdate\":\"2014-01-01\",\"todate\":\"2015-01-01\",\"date\":\"2023-02-01 18:57:25\"},{\"id\":280,\"job\":\"Junior Developer\",\"company\":\"Kraft Techex\",\"location\":\"USA\",\"description\":\"Description\",\"fromdate\":\"2014-01-01\",\"todate\":\"2015-01-01\",\"date\":\"2023-02-01 18:58:48\"},{\"id\":281,\"job\":\"Junior Developer\",\"company\":\"Kraft Techex\",\"location\":\"USA\",\"description\":\"Description\",\"fromdate\":\"2014-01-01\",\"todate\":\"2015-01-01\",\"date\":\"2023-02-01 18:58:59\"},{\"id\":282,\"job\":\"Junior Developer\",\"company\":\"Kraft Techex\",\"location\":\"USA\",\"description\":\"Description\",\"fromdate\":\"2014-01-01\",\"todate\":\"2015-01-01\",\"date\":\"2023-02-01 18:59:15\"},{\"id\":283,\"job\":\"Junior Developer\",\"company\":\"Kraft Techex\",\"location\":\"USA\",\"description\":\"Description\",\"fromdate\":\"2014-01-01\",\"todate\":\"2015-01-01\",\"date\":\"2023-02-01 20:08:11\"},{\"id\":284,\"job\":\"Junior Developer\",\"company\":\"Kraft Techex\",\"location\":\"USA\",\"description\":\"Description\",\"fromdate\":\"2014-01-01\",\"todate\":\"2015-01-01\",\"date\":\"2023-02-01 20:09:47\"}]},{\"id\":102,\"name\":\"GHAN\",\"email\":\"qateam@test.com\",\"password\":\"$2y$10$MDxJgGTXav9daQ68\\\/h5uneYz919JbeWeMFG83ztrfAQF5vs6qUNXe\",\"about\":\"about what\",\"terms\":\"2\",\"date\":\"2022-12-22 01:28:03\",\"job\":\"Test Automation Engineer\",\"company\":\"GHAN com\",\"website\":\"https:\\\/\\\/www.ghan.com\\\/\",\"location\":\"Nederland\",\"skills\":[\"PHP\",\"Java\"],\"github\":null,\"twitter\":null,\"facebook\":null,\"youtube\":null,\"linkedin\":null,\"instagram\":null,\"avatar\":\"1\",\"admin\":\"1\",\"education\":[{\"id\":115,\"school\":\"Delft Tecnologie University\",\"degree\":\"Becholar\",\"study\":\"Computer Science\",\"description\":\"Description\",\"fromdate\":\"2022-01-22\",\"todate\":\"2022-12-12\",\"date\":\"2022-12-22 01:40:31\"}],\"experience\":[{\"id\":180,\"job\":\"Junior Tester\",\"company\":\"Ghan Comp\",\"location\":\"NL\",\"description\":\"Description\",\"fromdate\":\"2019-01-01\",\"todate\":\"2022-12-12\",\"date\":\"2022-12-22 01:38:38\"}]},{\"id\":110,\"name\":\"Ali TANUpdated\",\"email\":\"ali@test.com\",\"password\":\"$2y$10$k3yJiw8MuuLLBiprxG40BuXL4zlwQiklDCdIP9p6LCaBLpuwz\\\/pri\",\"about\":\"Hello Admin\",\"terms\":\"2\",\"date\":\"2023-01-06 21:40:02\",\"job\":\"Tester\",\"company\":\"GHAN Software\",\"website\":\"https:\\\/\\\/www.ghan.com\\\/\",\"location\":\"NL\",\"skills\":[\"PHP\",\"Java\",\"Selenium\",\"\"],\"github\":null,\"twitter\":null,\"facebook\":null,\"youtube\":null,\"linkedin\":null,\"instagram\":null,\"avatar\":\"1\",\"admin\":\" 1\",\"education\":[{\"id\":117,\"school\":\"Delft\",\"degree\":\"Bachelor\",\"study\":\"Computor Science\",\"description\":\"Great University\",\"fromdate\":\"2023-09-09\",\"todate\":\"2026-06-06\",\"date\":\"2023-01-07 00:07:05\"}],\"experience\":[{\"id\":186,\"job\":\"Junior SDET\",\"company\":\"Ghan IT Com\",\"location\":\"NL\",\"description\":\"UI Auromation\",\"fromdate\":\"2020-01-01\",\"todate\":\"2023-01-06\",\"date\":\"2023-01-06 22:06:22\"},{\"id\":187,\"job\":\"SDET ANd  Developer\",\"company\":\"GHAN II IT BV\",\"location\":\"UK\",\"description\":\"Nice job\",\"fromdate\":\"2020-02-02\",\"todate\":\"2022-12-12\",\"date\":\"2023-01-06 22:10:26\"},{\"id\":188,\"job\":\"Junior SDET\",\"company\":\"Ghan IT Com\",\"location\":\"NL\",\"description\":\"UI Auromation\",\"fromdate\":\"2020-01-01\",\"todate\":\"2023-01-07\",\"date\":\"2023-01-07 19:09:23\"}]},{\"id\":111,\"name\":\"Thomas Eduson\",\"email\":\"thomas@test.com\",\"password\":\"$2y$10$Z9DQwewjhTKomyoGqKtl\\\/eCLCP4RJ6ouG7NBsSjUgpCppgzIrlARW\",\"about\":\"patch method tried\",\"terms\":\"2\",\"date\":\"2023-01-12 14:41:31\",\"job\":\"Developer\",\"company\":\"GHAN Software\",\"website\":\"https:\\\/\\\/www.ghan.com\\\/\",\"location\":\"Turkey\",\"skills\":[\"PHP\",\"Java\",\"Selenium\",\"Cypress\",\"SQL\"],\"github\":null,\"twitter\":null,\"facebook\":null,\"youtube\":null,\"linkedin\":null,\"instagram\":null,\"avatar\":\"1\",\"admin\":\" 1\",\"education\":[{\"id\":123,\"school\":\"ODTU\",\"degree\":\"Becholar\",\"study\":\"computer science\",\"description\":\"Good school\",\"fromdate\":\"2018-12-12\",\"todate\":\"2012-12-12\",\"date\":\"2023-01-12 14:49:47\"},{\"id\":124,\"school\":\"Delft University\",\"degree\":\"Master Degree\",\"study\":\"Computer Science\",\"description\":\"Great\",\"fromdate\":\"2019-10-10\",\"todate\":\"2022-05-08\",\"date\":\"2023-01-12 14:50:56\"}],\"experience\":[{\"id\":192,\"job\":\"Junior Developer\",\"company\":\"Kraft Techex\",\"location\":\"TR\",\"description\":\"Frontend developer\",\"fromdate\":\"2019-12-12\",\"todate\":\"2020-12-12\",\"date\":\"2023-01-12 14:46:25\"},{\"id\":193,\"job\":\"Junior Developer\",\"company\":\"Snool Software\",\"location\":\"UK\",\"description\":\"Frontend developer\",\"fromdate\":\"2017-12-12\",\"todate\":\"2019-12-12\",\"date\":\"2023-01-12 14:47:25\"}]},{\"id\":122,\"name\":\"aaaFm\",\"email\":\"asl\\u0131@asl\\u0131.com\",\"password\":\"$2y$10$sT49fVo1mNr\\\/FttWlMgMJePS\\\/8RwAKSyyWt\\\/Sqbmmf5Pmff.s9s4a\",\"about\":\"About\",\"terms\":\"2\",\"date\":\"2023-01-16 21:43:59\",\"job\":\"Developer\",\"company\":\"Mrcn Software\",\"website\":\"https:\\\/\\\/www.krafttechexlab.com\\\/\",\"location\":\"Turkey\",\"skills\":[\"PHP\",\"Java\"],\"github\":null,\"twitter\":null,\"facebook\":null,\"youtube\":null,\"linkedin\":null,\"instagram\":null,\"avatar\":\"1\",\"admin\":\"0 or 1\",\"education\":[],\"experience\":[]},{\"id\":131,\"name\":\"Eliza Gehart\",\"email\":\"eliza@test.com\",\"password\":\"$2y$10$nbAs8\\\/7hUht4c2svW1JfcuvgDgrVTMfRqi0XDEWkJgplmoC3HVMEK\",\"about\":\"About Me\",\"terms\":\"10\",\"date\":\"2023-01-25 10:12:18\",\"job\":\"SDET\",\"company\":\"GHAN Software\",\"website\":\"https:\\\/\\\/www.ghan.com\\\/\",\"location\":\"UK\",\"skills\":[\"PHP\",\"Java\",\"API\"],\"github\":null,\"twitter\":null,\"facebook\":null,\"youtube\":null,\"linkedin\":null,\"instagram\":null,\"avatar\":\"1\",\"admin\":\"0\",\"education\":[],\"experience\":[]},{\"id\":366,\"name\":\"Ms. Justin Hand\",\"email\":\"Allene.Mohr17@hotmail.com\",\"password\":\"$2y$10$gS1uMJuO144HfaLjcifjC.YLEQ\\\/41ncLoV8sTPn\\\/iNSAvpD7sXeGy\",\"about\":\"About\",\"terms\":\"2\",\"date\":\"2023-02-01 19:53:41\",\"job\":\"Developer\",\"company\":\"Rau - Dare\",\"website\":\"https:\\\/\\\/hilbert.name\",\"location\":\"{{randonCity}}\",\"skills\":[\"PHP\",\"Java\"],\"github\":null,\"twitter\":null,\"facebook\":null,\"youtube\":null,\"linkedin\":null,\"instagram\":null,\"avatar\":\"1\",\"admin\":\"0 or 1\",\"education\":[],\"experience\":[{\"id\":287,\"job\":\"Junior Developer\",\"company\":\"Braun, Kris and Brekke\",\"location\":\"Makennamouth\",\"description\":\"Description\",\"fromdate\":\"2015-01-01\",\"todate\":\"2022-01-01\",\"date\":\"2023-02-01 21:48:13\"},{\"id\":289,\"job\":\"SDET\",\"company\":\"Howell - O'Hara\",\"location\":\"Turkey\",\"description\":\"Description\",\"fromdate\":\"2022-01-02\",\"todate\":\"2023-02-02\",\"date\":\"2023-02-01 21:48:16\"},{\"id\":295,\"job\":\"Junior Developer\",\"company\":\"Daniel, Kris and Gorczany\",\"location\":\"Port Ethylport\",\"description\":\"Description\",\"fromdate\":\"2010-01-01\",\"todate\":\"2011-01-01\",\"date\":\"2023-02-01 21:48:46\"},{\"id\":298,\"job\":\"Junior Developer\",\"company\":\"Beier Inc\",\"location\":\"South Eldred\",\"description\":\"Description\",\"fromdate\":\"2010-01-01\",\"todate\":\"2011-01-01\",\"date\":\"2023-02-01 21:50:17\"},{\"id\":317,\"job\":\"Junior Developer\",\"company\":\"Koss and Sons\",\"location\":\"Antelope\",\"description\":\"Description\",\"fromdate\":\"2015-01-01\",\"todate\":\"2022-01-01\",\"date\":\"2023-02-02 20:18:36\"},{\"id\":319,\"job\":\"Junior Developer\",\"company\":\"O'Hara, Kessler and Koelpin\",\"location\":\"Kittymouth\",\"description\":\"Description\",\"fromdate\":\"2015-01-01\",\"todate\":\"2022-01-01\",\"date\":\"2023-02-02 20:22:14\"},{\"id\":336,\"job\":\"Junior Developer\",\"company\":\"Hickle, Herman and Pollich\",\"location\":\"West Abagail\",\"description\":\"Description\",\"fromdate\":\"2015-01-01\",\"todate\":\"2022-01-01\",\"date\":\"2023-02-02 20:44:52\"},{\"id\":395,\"job\":\"Junior Developer\",\"company\":\"Rippin, Hoppe and Huel\",\"location\":\"Lake Zoey\",\"description\":\"Description\",\"fromdate\":\"2015-01-01\",\"todate\":\"2022-01-01\",\"date\":\"2023-02-02 20:50:11\"},{\"id\":414,\"job\":\"Junior Developer\",\"company\":\"Langosh, Brakus and Goldner\",\"location\":\"Lefflerfort\",\"description\":\"Description\",\"fromdate\":\"2015-01-01\",\"todate\":\"2022-01-01\",\"date\":\"2023-02-02 20:57:30\"},{\"id\":421,\"job\":\"Junior Developer\",\"company\":\"Doyle and Sons\",\"location\":\"Port Favian\",\"description\":\"Description\",\"fromdate\":\"2015-01-01\",\"todate\":\"2022-01-01\",\"date\":\"2023-02-02 20:58:50\"}]},{\"id\":369,\"name\":\"Tom Kassulke\",\"email\":\"Jakob.White@gmail.com\",\"password\":\"$2y$10$d0s5LmueD0TY6iWx0tr4\\\/OZ1UdFSNpk3zkIlLr5eE7D\\\/TW.8egDWK\",\"about\":\"About\",\"terms\":\"2\",\"date\":\"2023-02-01 20:37:13\",\"job\":\"Developer\",\"company\":\"Feil - Beier\",\"website\":\"https:\\\/\\\/terrell.info\",\"location\":\"West Samsonstad\",\"skills\":[\"PHP\",\"Java\"],\"github\":null,\"twitter\":null,\"facebook\":null,\"youtube\":null,\"linkedin\":null,\"instagram\":null,\"avatar\":\"1\",\"admin\":\"0 or 1\",\"education\":[],\"experience\":[]},{\"id\":374,\"name\":\"Mrs. Jo McKenzie\",\"email\":\"Kyla18@hotmail.com\",\"password\":\"$2y$10$IvLCvFk21uHLn4vjQfRil.GtBIQR96ukzB.WF.ohrRI9NwTeXstI.\",\"about\":\"About\",\"terms\":\"2\",\"date\":\"2023-02-01 20:40:41\",\"job\":\"Developer\",\"company\":\"Will - Grady\",\"website\":\"https:\\\/\\\/bianka.org\",\"location\":\"Sawaynshire\",\"skills\":[\"PHP\",\"Java\"],\"github\":null,\"twitter\":null,\"facebook\":null,\"youtube\":null,\"linkedin\":null,\"instagram\":null,\"avatar\":\"1\",\"admin\":\"0 or 1\",\"education\":[],\"experience\":[{\"id\":429,\"job\":\"Junior Developer\",\"company\":\"Rutherford Group\",\"location\":\"Port Rainahaven\",\"description\":\"Description\",\"fromdate\":\"2011-02-03\",\"todate\":\"2012-05-06\",\"date\":\"2023-02-02 21:00:38\"}]},{\"id\":375,\"name\":\"Jose Marquardt\",\"email\":\"Marjory.Runolfsson80@gmail.com\",\"password\":\"$2y$10$TDY.sFIKPdxDuSFEZq8tZee7zniFQ6gy.TWRn0Xqy0AWGOd2BL2Qu\",\"about\":\"About\",\"terms\":\"2\",\"date\":\"2023-02-01 20:40:47\",\"job\":\"Developer\",\"company\":\"Thompson, Price and Hamill\",\"website\":\"http:\\\/\\\/margret.net\",\"location\":\"Olsonmouth\",\"skills\":[\"PHP\",\"Java\"],\"github\":null,\"twitter\":null,\"facebook\":null,\"youtube\":null,\"linkedin\":null,\"instagram\":null,\"avatar\":\"1\",\"admin\":\"0 or 1\",\"education\":[],\"experience\":[{\"id\":290,\"job\":\"Junior Developer\",\"company\":\"Mertz - Little\",\"location\":\"South Mallory\",\"description\":\"Description\",\"fromdate\":\"2010-01-01\",\"todate\":\"2011-01-01\",\"date\":\"2023-02-01 21:48:17\"},{\"id\":302,\"job\":\"Junior Developer\",\"company\":\"Fisher - Kuhic\",\"location\":\"Lake Matildaburgh\",\"description\":\"Description\",\"fromdate\":\"2010-01-01\",\"todate\":\"2011-01-01\",\"date\":\"2023-02-01 22:09:55\"},{\"id\":303,\"job\":\"Senior QA\",\"company\":\"Defacto\",\"location\":\"Lake Leathaton\",\"description\":\"Description\",\"fromdate\":\"2012-02-02\",\"todate\":\"2022-02-20\",\"date\":\"2023-02-01 22:11:02\"},{\"id\":331,\"job\":\"Junior Developer\",\"company\":\"Sipes and Sons\",\"location\":\"Brodyside\",\"description\":\"Description\",\"fromdate\":\"2010-01-01\",\"todate\":\"2011-01-01\",\"date\":\"2023-02-02 20:42:09\"},{\"id\":410,\"job\":\"Junior Developer\",\"company\":\"Gorczany, Hyatt and Schimmel\",\"location\":\"East Websterfurt\",\"description\":\"Description\",\"fromdate\":\"2010-01-01\",\"todate\":\"2011-01-01\",\"date\":\"2023-02-02 20:56:20\"}]},{\"id\":376,\"name\":\"Marie Heidenreich\",\"email\":\"Winona39@yahoo.com\",\"password\":\"$2y$10$I3Z7GwngXiSvUYU.82fBsOaX8BApz0CQl3sIZ1dy2ZcbNHznKgo4G\",\"about\":\"About\",\"terms\":\"2\",\"date\":\"2023-02-01 20:40:48\",\"job\":\"Developer\",\"company\":\"Mayer - Kuphal\",\"website\":\"https:\\\/\\\/alberto.net\",\"location\":\"Taylorsville\",\"skills\":[\"PHP\",\"Java\"],\"github\":null,\"twitter\":null,\"facebook\":null,\"youtube\":null,\"linkedin\":null,\"instagram\":null,\"avatar\":\"1\",\"admin\":\"0 or 1\",\"education\":[],\"experience\":[]},{\"id\":377,\"name\":\"Drew Dicki\",\"email\":\"Noelia.McDermott@gmail.com\",\"password\":\"$2y$10$6EaUOIwQ3CSsSiHkYlRXwu8f7mw\\\/EiA.IPEwDKOoB46x5OytF0pTC\",\"about\":\"About\",\"terms\":\"2\",\"date\":\"2023-02-01 20:40:49\",\"job\":\"Developer\",\"company\":\"McGlynn Group\",\"website\":\"https:\\\/\\\/jordan.biz\",\"location\":\"Zboncakstad\",\"skills\":[\"PHP\",\"Java\"],\"github\":null,\"twitter\":null,\"facebook\":null,\"youtube\":null,\"linkedin\":null,\"instagram\":null,\"avatar\":\"1\",\"admin\":\"0 or 1\",\"education\":[],\"experience\":[{\"id\":326,\"job\":\"King SDET\",\"company\":\"Kraft Ondricka - McKenzie\",\"location\":\"Faybury\",\"description\":\"Description\",\"fromdate\":\"2000-11-11\",\"todate\":\"2002-11-11\",\"date\":\"2023-02-02 20:41:27\"},{\"id\":332,\"job\":\"King SDET\",\"company\":\"Kraft Buckridge - Kuhic\",\"location\":\"East Kaitlin\",\"description\":\"Description\",\"fromdate\":\"2000-11-11\",\"todate\":\"2002-11-11\",\"date\":\"2023-02-02 20:42:53\"}]},{\"id\":378,\"name\":\"Lora Schuster\",\"email\":\"Lessie.Von@hotmail.com\",\"password\":\"$2y$10$DUPSOvRAYlMhHNwjDxz91eziApmmq2hImAT5b\\\/LVSK2ultZBvKALy\",\"about\":\"QA\",\"terms\":\"3\",\"date\":\"2023-02-01 20:40:53\",\"job\":\"Senior SDET\",\"company\":\"Zemlak LLC\",\"website\":\"https:\\\/\\\/selina.name\",\"location\":\"West Simborough\",\"skills\":[\"PHP\",\"Java\"],\"github\":null,\"twitter\":null,\"facebook\":null,\"youtube\":null,\"linkedin\":null,\"instagram\":null,\"avatar\":\"1\",\"admin\":\"0 or 1\",\"education\":[],\"experience\":[{\"id\":363,\"job\":\"Senior QA\",\"company\":\"Tromp Group\",\"location\":\"Lake Chadd\",\"description\":\"Specialist\",\"fromdate\":\"2018-11-11\",\"todate\":\"2020-11-11\",\"date\":\"2023-02-02 20:45:28\"}]},{\"id\":379,\"name\":\"Christian Sanford DVM\",\"email\":\"Lionel_Brakus86@hotmail.com\",\"password\":\"$2y$10$n6Q5p3OQCsBlfHvD9Anm4eFJpv1mt.NxqgA2TDMPt\\\/.hOuwQRz0je\",\"about\":\"About\",\"terms\":\"2\",\"date\":\"2023-02-01 20:40:56\",\"job\":\"Developer\",\"company\":\"Morissette Group\",\"website\":\"https:\\\/\\\/columbus.info\",\"location\":\"Valdosta\",\"skills\":[\"PHP\",\"Java\"],\"github\":null,\"twitter\":null,\"facebook\":null,\"youtube\":null,\"linkedin\":null,\"instagram\":null,\"avatar\":\"1\",\"admin\":\"0 or 1\",\"education\":[],\"experience\":[{\"id\":355,\"job\":\"Developer \\u0130n Test\",\"company\":\"Lemke - Walter\",\"location\":\"Port Jordiberg\",\"description\":\"Description\",\"fromdate\":\"2022-12-25\",\"todate\":\"2023-02-02\",\"date\":\"2023-02-02 20:45:24\"},{\"id\":380,\"job\":\"Developer \\u0130n Test\",\"company\":\"Becker - Howe\",\"location\":\"South Kelton\",\"description\":\"Description\",\"fromdate\":\"2022-12-25\",\"todate\":\"2023-02-02\",\"date\":\"2023-02-02 20:47:12\"},{\"id\":381,\"job\":\"Developer \\u0130n Test\",\"company\":\"Armstrong, Rutherford and Kessler\",\"location\":\"Lake Abelardo\",\"description\":\"Description\",\"fromdate\":\"2022-12-25\",\"todate\":\"2023-02-02\",\"date\":\"2023-02-02 20:48:50\"},{\"id\":392,\"job\":\"Developer \\u0130n Test\",\"company\":\"Will, Feil and Hermiston\",\"location\":\"West Aronland\",\"description\":\"Description\",\"fromdate\":\"2022-12-25\",\"todate\":\"2023-02-02\",\"date\":\"2023-02-02 20:49:43\"},{\"id\":394,\"job\":\"Developer \\u0130n Test\",\"company\":\"Mitchell and Sons\",\"location\":\"Zacharyberg\",\"description\":\"Description\",\"fromdate\":\"2022-12-25\",\"todate\":\"2023-02-02\",\"date\":\"2023-02-02 20:50:03\"},{\"id\":399,\"job\":\"Developer \\u0130n Test\",\"company\":\"Koch Inc\",\"location\":\"Powlowskiberg\",\"description\":\"Description\",\"fromdate\":\"2022-12-25\",\"todate\":\"2023-02-02\",\"date\":\"2023-02-02 20:51:07\"},{\"id\":400,\"job\":\"Developer \\u0130n Test\",\"company\":\"Lowe, Kulas and O'Connell\",\"location\":\"Cheektowaga\",\"description\":\"Description\",\"fromdate\":\"2022-12-25\",\"todate\":\"2023-02-02\",\"date\":\"2023-02-02 20:51:46\"},{\"id\":411,\"job\":\"Developer \\u0130n Test\",\"company\":\"Marquardt, Mills and Reichert\",\"location\":\"Port Donavon\",\"description\":\"Description\",\"fromdate\":\"2022-12-25\",\"todate\":\"2023-02-02\",\"date\":\"2023-02-02 20:56:44\"},{\"id\":412,\"job\":\"Developer \\u0130n Test\",\"company\":\"Sauer - Barton\",\"location\":\"Rodriguezchester\",\"description\":\"Description\",\"fromdate\":\"2022-12-25\",\"todate\":\"2023-02-02\",\"date\":\"2023-02-02 20:57:05\"},{\"id\":415,\"job\":\"Developer \\u0130n Test\",\"company\":\"Dicki, Gislason and Ruecker\",\"location\":\"South Seanburgh\",\"description\":\"Description\",\"fromdate\":\"2022-12-25\",\"todate\":\"2023-02-02\",\"date\":\"2023-02-02 20:57:55\"},{\"id\":419,\"job\":\"Developer \\u0130n Test\",\"company\":\"McCullough - Fritsch\",\"location\":\"Dietrichland\",\"description\":\"Description\",\"fromdate\":\"2022-12-25\",\"todate\":\"2023-02-02\",\"date\":\"2023-02-02 20:58:19\"},{\"id\":424,\"job\":\"Developer \\u0130n Test\",\"company\":\"Cassin - Klocko\",\"location\":\"Tucson\",\"description\":\"Description\",\"fromdate\":\"2022-12-25\",\"todate\":\"2023-02-02\",\"date\":\"2023-02-02 20:59:05\"},{\"id\":425,\"job\":\"Developer \\u0130n Test\",\"company\":\"Pfeffer, Cummerata and Farrell\",\"location\":\"Caterinachester\",\"description\":\"Description\",\"fromdate\":\"2022-12-25\",\"todate\":\"2023-02-02\",\"date\":\"2023-02-02 20:59:17\"},{\"id\":427,\"job\":\"Developer \\u0130n Test\",\"company\":\"Sanford, Hintz and Hermiston\",\"location\":\"Ileneborough\",\"description\":\"Description\",\"fromdate\":\"2022-12-25\",\"todate\":\"2023-02-02\",\"date\":\"2023-02-02 21:00:00\"}]},{\"id\":381,\"name\":\"aFm03\",\"email\":\"aliveli3@krafttechexlab.com\",\"password\":\"$2y$10$9Q5A1u6cvAykShmZ1XGmR.Q8m2lnOhqNc8vPAsh86kf20CGDVIp5u\",\"about\":\"About\",\"terms\":\"2\",\"date\":\"2023-02-01 20:41:08\",\"job\":\"Developer\",\"company\":\"Mrcn Software03\",\"website\":\"https:\\\/\\\/www.krafttechexlab.com\\\/\",\"location\":\"Turkey\",\"skills\":[\"PHP\",\"Java\"],\"github\":null,\"twitter\":null,\"facebook\":null,\"youtube\":null,\"linkedin\":null,\"instagram\":null,\"avatar\":\"1\",\"admin\":\"0 or 1\",\"education\":[],\"experience\":[]},{\"id\":385,\"name\":\"aJesus Lynch\",\"email\":\"Reynold_Brown@hotmail.com\",\"password\":\"$2y$10$OgL8dLthUEJozLuYAdV8Mel6jxVVKzKrp1zw7Oow\\\/9Q4Ez.Lsu0Lu\",\"about\":\"About\",\"terms\":\"2\",\"date\":\"2023-02-01 20:43:39\",\"job\":\"Developer\",\"company\":\"Lehner - Beahan\",\"website\":\"https:\\\/\\\/vidal.info\",\"location\":\"Turkey\",\"skills\":[\"PHP\",\"Java\"],\"github\":null,\"twitter\":null,\"facebook\":null,\"youtube\":null,\"linkedin\":null,\"instagram\":null,\"avatar\":\"1\",\"admin\":\"0 or 1\",\"education\":[],\"experience\":[{\"id\":294,\"job\":\"SDET\",\"company\":\"Ms.Kraft \",\"location\":\"Port Elsetown\",\"description\":\"Description\",\"fromdate\":\"2011-08-08\",\"todate\":\"2012-08-08\",\"date\":\"2023-02-01 21:48:36\"},{\"id\":325,\"job\":\"Junior Developer\",\"company\":\"Mr.Kraft\",\"location\":\"Bristol\",\"description\":\"Description\",\"fromdate\":\"2011-08-08\",\"todate\":\"2012-08-08\",\"date\":\"2023-02-02 20:41:26\"}]},{\"id\":389,\"name\":\"Mr. Ronald Raynor\",\"email\":\"Stone_Rutherford@gmail.com\",\"password\":\"$2y$10$wVZW9iEhClJpqH7aWhpWRu1HIrSr.g\\\/.weCY3SY.sm8o.faVbCuJS\",\"about\":\"About\",\"terms\":\"2\",\"date\":\"2023-02-01 20:59:03\",\"job\":\"Developer\",\"company\":\"Walter Inc\",\"website\":\"https:\\\/\\\/alayna.biz\",\"location\":\"Turkey\",\"skills\":[\"PHP\",\"Java\"],\"github\":null,\"twitter\":null,\"facebook\":null,\"youtube\":null,\"linkedin\":null,\"instagram\":null,\"avatar\":\"1\",\"admin\":\"0 or 1\",\"education\":[{\"id\":323,\"school\":\"McGlynn and Sons school\",\"degree\":\"phd\",\"study\":\"ARCHIVE\",\"description\":\"Description\",\"fromdate\":\"2011-12-11\",\"todate\":\"2011-10-23\",\"date\":\"2023-02-02 22:02:38\"}],\"experience\":[{\"id\":299,\"job\":\"Junior Developer\",\"company\":\"McGlynn - Runolfsdottir\",\"location\":\"North Miraclemouth\",\"description\":\"Description\",\"fromdate\":\"2012-01-01\",\"todate\":\"2012-01-11\",\"date\":\"2023-02-01 21:50:29\"},{\"id\":300,\"job\":\"Junior Developer\",\"company\":\"Huels, Thiel and Hoeger\",\"location\":\"North Zane\",\"description\":\"Description\",\"fromdate\":\"2012-01-01\",\"todate\":\"2012-01-11\",\"date\":\"2023-02-01 21:54:12\"},{\"id\":472,\"job\":\"Junior Developer\",\"company\":\"McGlynn, Beahan and Hettinger\",\"location\":\"Rosenbaumshire\",\"description\":\"Description\",\"fromdate\":\"2012-01-01\",\"todate\":\"2012-01-11\",\"date\":\"2023-02-02 21:54:06\"},{\"id\":491,\"job\":\"Junior Developer\",\"company\":\"Runolfsson, Runolfsson and Beier\",\"location\":\"Vallejo\",\"description\":\"Description\",\"fromdate\":\"2012-01-01\",\"todate\":\"2012-01-11\",\"date\":\"2023-02-02 22:07:42\"}]},{\"id\":393,\"name\":\"Antonio Haley\",\"email\":\"Ari77@hotmail.com\",\"password\":\"$2y$10$JYpWmp9GVVhzD\\\/RkCl5NauC4kBCWW3HSJ01jstqhP0K.8DamQleQG\",\"about\":\"About\",\"terms\":\"2\",\"date\":\"2023-02-02 11:56:40\",\"job\":\"Developer\",\"company\":\"Bergstrom Group\",\"website\":\"https:\\\/\\\/odessa.com\",\"location\":\"Alessandrafurt\",\"skills\":[\"PHP\",\"Java\"],\"github\":null,\"twitter\":null,\"facebook\":null,\"youtube\":null,\"linkedin\":null,\"instagram\":null,\"avatar\":\"1\",\"admin\":\"0 or 1\",\"education\":[],\"experience\":[{\"id\":310,\"job\":\"SDET\",\"company\":\"Mr.Kraft \",\"location\":\"North Zolaton\",\"description\":\"Description\",\"fromdate\":\"2011-08-08\",\"todate\":\"2012-08-08\",\"date\":\"2023-02-02 16:06:21\"}]},{\"id\":398,\"name\":\"Ashley Nolan\",\"email\":\"Anne_Wehner11@hotmail.com\",\"password\":\"$2y$10$zCi7dMLIX0NNLnbxW8kqFuOkcapMbBN0IbujdIdVeXflWZ4hJNtjq\",\"about\":\"About\",\"terms\":\"2\",\"date\":\"2023-02-02 16:47:59\",\"job\":\"Developer\",\"company\":\"Murray Group\",\"website\":\"http:\\\/\\\/manuel.info\",\"location\":\"West Trevorton\",\"skills\":[\"PHP\",\"Java\"],\"github\":null,\"twitter\":null,\"facebook\":null,\"youtube\":null,\"linkedin\":null,\"instagram\":null,\"avatar\":\"1\",\"admin\":\"0 or 1\",\"education\":[],\"experience\":[{\"id\":329,\"job\":\"SDET\",\"company\":\"Ms.Kraftech \",\"location\":\"Draper\",\"description\":\"Description\",\"fromdate\":\"2011-08-08\",\"todate\":\"2012-08-08\",\"date\":\"2023-02-02 20:41:33\"}]},{\"id\":400,\"name\":\"Robin Lubowitz\",\"email\":\"Mertie72@yahoo.com\",\"password\":\"$2y$10$xgSQON2tiRQTqckkVoKdm.svSmeI01dBKdCqxEIJepLZAfExt4KO2\",\"about\":\"About\",\"terms\":\"2\",\"date\":\"2023-02-02 17:12:44\",\"job\":\"Developer\",\"company\":\"Tremblay Group\",\"website\":\"https:\\\/\\\/www.krafttechexlab.com\\\/\",\"location\":\"Turkey\",\"skills\":[\"PHP\",\"Java\"],\"github\":null,\"twitter\":null,\"facebook\":null,\"youtube\":null,\"linkedin\":null,\"instagram\":null,\"avatar\":\"1\",\"admin\":\"0 or 1\",\"education\":[],\"experience\":[]},{\"id\":430,\"name\":\"Ashley Nolan\",\"email\":\"Reyes29@hotmail.com\",\"password\":\"$2y$10$7\\\/l.cn9x8YA.t8\\\/R5POayu7Zt.AZOP5Q00eQ1QC8xYi0Fv2FU8ZFy\",\"about\":\"About\",\"terms\":\"2\",\"date\":\"2023-02-02 20:51:35\",\"job\":\"Developer\",\"company\":\"White Group\",\"website\":\"http:\\\/\\\/elody.org\",\"location\":\"New Lafayette\",\"skills\":[\"PHP\",\"Java\"],\"github\":null,\"twitter\":null,\"facebook\":null,\"youtube\":null,\"linkedin\":null,\"instagram\":null,\"avatar\":\"1\",\"admin\":\"0 or 1\",\"education\":[],\"experience\":[]},{\"id\":434,\"name\":\"Mattie Gorczany\",\"email\":\"Tremaine.Hane64@yahoo.com\",\"password\":\"$2y$10$uvPOkSyKHSGqq\\\/IcVRNvH.jLNl6PseJSbZfmcVTSqwL6nb3PCPLWS\",\"about\":\"About\",\"terms\":\"2\",\"date\":\"2023-02-02 20:52:12\",\"job\":\"Developer\",\"company\":\"Grant Inc\",\"website\":\"https:\\\/\\\/ryann.info\",\"location\":\"Roseville\",\"skills\":[\"PHP\",\"Java\"],\"github\":null,\"twitter\":null,\"facebook\":null,\"youtube\":null,\"linkedin\":null,\"instagram\":null,\"avatar\":\"1\",\"admin\":\"0 or 1\",\"education\":[],\"experience\":[]},{\"id\":449,\"name\":\"Ashley Nolan\",\"email\":\"Marilie_Roberts@gmail.com\",\"password\":\"$2y$10$5Sx\\\/FCj2V2SsZNSX.BSxlOyrfqdACOFoWNnADyQjxUGWJBsJupZLq\",\"about\":\"About\",\"terms\":\"2\",\"date\":\"2023-02-02 20:53:08\",\"job\":\"Developer\",\"company\":\"Dickinson - Nader\",\"website\":\"https:\\\/\\\/terrance.net\",\"location\":\"Lake Reinaberg\",\"skills\":[\"PHP\",\"Java\"],\"github\":null,\"twitter\":null,\"facebook\":null,\"youtube\":null,\"linkedin\":null,\"instagram\":null,\"avatar\":\"1\",\"admin\":\"0 or 1\",\"education\":[],\"experience\":[]},{\"id\":452,\"name\":\"Ashley Nolan\",\"email\":\"Jennifer.Lehner20@yahoo.com\",\"password\":\"$2y$10$OABXG62eTHQeWJsaHTl2a.Mm1FKXHWGzMj1TFABCEDVzja4OVb8U.\",\"about\":\"About\",\"terms\":\"2\",\"date\":\"2023-02-02 20:53:13\",\"job\":\"Developer\",\"company\":\"Waelchi LLC\",\"website\":\"http:\\\/\\\/martine.name\",\"location\":\"Carleestad\",\"skills\":[\"PHP\",\"Java\"],\"github\":null,\"twitter\":null,\"facebook\":null,\"youtube\":null,\"linkedin\":null,\"instagram\":null,\"avatar\":\"1\",\"admin\":\"0 or 1\",\"education\":[],\"experience\":[]}]","line":126}},{"name":"status 200","result":{"duration":12900,"status":"passed"},"match":{"location":"karate","arguments":[]},"keyword":"*","line":127},{"name":"match header Content-Type == 'application\/json; charset=UTF-8'","result":{"duration":443700,"status":"passed"},"match":{"location":"karate","arguments":[]},"keyword":"*","line":130},{"name":"print response[0].name","result":{"duration":6633800,"status":"passed"},"match":{"location":"karate","arguments":[]},"keyword":"*","line":131,"doc_string":{"content_type":"","value":"23:25:43.111 [print] MercanS","line":131}},{"name":"print response[0].skills","result":{"duration":6090200,"status":"passed"},"match":{"location":"karate","arguments":[]},"keyword":"*","line":132,"doc_string":{"content_type":"","value":"23:25:43.117 [print] [\n  \"PHP\",\n  \"Java\"\n]","line":132}},{"name":"match response[0].skills == [\"PHP\", \"Java\"]","result":{"duration":495900,"status":"passed"},"match":{"location":"karate","arguments":[]},"keyword":"Then","line":135},{"name":"match response[0].name == 'MercanS'","result":{"duration":3708000,"status":"passed"},"match":{"location":"karate","arguments":[]},"keyword":"*","line":136},{"name":"match each response[*].id == '#number'","result":{"duration":4426800,"status":"passed"},"match":{"location":"karate","arguments":[]},"keyword":"Then","line":140}]}],"name":"features\/parametersTest.feature","description":"Parameters","id":"parameters","keyword":"Feature","uri":"features\/parametersTest.feature"}]